Metadata-Version: 1.0
Name: magic-metrics
Version: 1.0
Summary: ML Metrics library
Home-page: UNKNOWN
Author: UNKNOWN
Author-email: mshmnv@yandex.ru
License: UNKNOWN
Platform: UNKNOWN
